evola/__init__.py
evola/epso/__init__.py
evola/epso/academic_version/__init__.py
evola/epso/academic_version/particle.py
evola/epso/academic_version/simulation.py
evola/epso/academic_version/swarm.py
evola/epso/performance_version.py
evola/population.py
evola/scene.py
evola/simulation.py
evola/solution.py
evola-0.0.11.dist-info/METADATA
evola-0.0.11.dist-info/WHEEL
evola-0.0.11.dist-info/RECORD
