Metadata-Version: 2.1
Name: evola
Version: 0.0.11
Summary: Evolutionary algorithms
Home-page: https://github.com/DavidFreire-FEUP/evolutionary-algorithms
License: MIT
Author: David Freire
Author-email: up201806711@up.pt
Requires-Python: >3.8
Classifier: License :: OSI Approved :: MIT License
Classifier: Programming Language :: Python :: 3
Classifier: Programming Language :: Python :: 3.9
Classifier: Programming Language :: Python :: 3.10
Classifier: Programming Language :: Python :: 3.11
Requires-Dist: tqdm (>=4.66.1,<5.0.0)
Project-URL: Repository, https://github.com/DavidFreire-FEUP/evolutionary-algorithms
